embodiedcity/__init__.py
embodiedcity/client.py
embodiedcity-0.3.0.dist-info/LICENSE
embodiedcity-0.3.0.dist-info/METADATA
embodiedcity-0.3.0.dist-info/WHEEL
embodiedcity-0.3.0.dist-info/RECORD
