Metadata-Version: 2.1
Name: embodiedcity
Version: 0.3.0
Summary: Embodied City Python SDK
Home-page: https://embodied-city.fiblab.net
License: MIT
Keywords: city,embodied
Author: Jun Zhang
Author-email: zhangjun990222@qq.com
Requires-Python: >=3.10,<4.0
Classifier: License :: OSI Approved :: MIT License
Classifier: Operating System :: OS Independent
Classifier: Programming Language :: Python :: 3
Classifier: Programming Language :: Python :: 3.10
Classifier: Programming Language :: Python :: 3.11
Classifier: Programming Language :: Python :: 3.12
Requires-Dist: aiohttp[speedups] (>=3,<4)
Requires-Dist: numpy (>=1,<2)
Requires-Dist: opencv-python (>=4,<5)
Requires-Dist: pyproj (>=3,<4)
Requires-Dist: requests (>=2,<3)
Requires-Dist: shapely (>=2,<3)
Project-URL: Documentation, https://embodied-city.fiblab.net/docs
